{
  "_class": "shapePath",
  "booleanOperation": -1,
  "do_objectID": "91AAF0B2-8114-4360-B04C-819D793A7C2B",
  "edited": true,
  "exportOptions": {
    "_class": "exportOptions",
    "exportFormats": [
    ],
    "includedLayerIds": [
    ],
    "layerOptions": 0,
    "shouldTrim": false
  },
  "frame": {
    "_class": "rect",
    "constrainProportions": false,
    "height": 160.5135502078603,
    "width": 120,
    "x": 0,
    "y": -1.4210854715202e-13
  },
  "isClosed": false,
  "isFlippedHorizontal": false,
  "isFlippedVertical": false,
  "isLocked": false,
  "isVisible": true,
  "layerListExpandedType": 0,
  "name": "Path",
  "nameIsFixed": false,
  "path": {
    "_class": "path",
    "isClosed": false,
    "pointRadiusBehaviour": 1,
    "points": [
      {
        "_class": "curvePoint",
        "cornerRadius": 0,
        "curveFrom": "{0, 0.11950112736912494}",
        "curveMode": 4,
        "curveTo": "{0, 1}",
        "hasCurveFrom": true,
        "hasCurveTo": false,
        "point": "{0, 1}"
      },
      {
        "_class": "curvePoint",
        "cornerRadius": 0,
        "curveFrom": "{1, 0.10287947769191896}",
        "curveMode": 4,
        "curveTo": "{0.33333333333333331, -0.17953904673356874}",
        "hasCurveFrom": false,
        "hasCurveTo": true,
        "point": "{1, 0.10287947769191896}"
      }
    ]
  },
  "pointRadiusBehaviour": 1,
  "points": [
    {
      "_class": "curvePoint",
      "cornerRadius": 0,
      "curveFrom": "{0, 0.11950112736912494}",
      "curveMode": 4,
      "curveTo": "{0, 1}",
      "hasCurveFrom": true,
      "hasCurveTo": false,
      "point": "{0, 1}"
    },
    {
      "_class": "curvePoint",
      "cornerRadius": 0,
      "curveFrom": "{1, 0.10287947769191896}",
      "curveMode": 4,
      "curveTo": "{0.33333333333333331, -0.17953904673356874}",
      "hasCurveFrom": false,
      "hasCurveTo": true,
      "point": "{1, 0.10287947769191896}"
    }
  ],
  "resizingConstraint": 63,
  "resizingType": 0,
  "rotation": 0,
  "shouldBreakMaskChain": false
}