{
  "_class": "shapePath",
  "booleanOperation": -1,
  "do_objectID": "E5ED7B17-7AFA-4071-90EB-A9A31D3D4191",
  "edited": true,
  "exportOptions": {
    "_class": "exportOptions",
    "exportFormats": [
    ],
    "includedLayerIds": [
    ],
    "layerOptions": 0,
    "shouldTrim": false
  },
  "frame": {
    "_class": "rect",
    "constrainProportions": false,
    "height": 27,
    "width": 27,
    "x": 0,
    "y": 0
  },
  "isClosed": false,
  "isFlippedHorizontal": false,
  "isFlippedVertical": false,
  "isLocked": false,
  "isVisible": true,
  "layerListExpandedType": 0,
  "name": "Path",
  "nameIsFixed": false,
  "path": {
    "_class": "path",
    "isClosed": false,
    "pointRadiusBehaviour": 0,
    "points": [
      {
        "_class": "curvePoint",
        "cornerRadius": 0,
        "curveFrom": "{0.97314814814815154, 0.99444444444444524}",
        "curveMode": 4,
        "curveTo": "{0.98392592592592709, 0.98333333333333162}",
        "hasCurveFrom": true,
        "hasCurveTo": false,
        "point": "{0.98392592592592709, 0.98333333333333162}"
      },
      {
        "_class": "curvePoint",
        "cornerRadius": 0,
        "curveFrom": "{0.94444444444444442, 1}",
        "curveMode": 4,
        "curveTo": "{0.96000000000000274, 1}",
        "hasCurveFrom": false,
        "hasCurveTo": true,
        "point": "{0.94444444444444442, 1}"
      },
      {
        "_class": "curvePoint",
        "cornerRadius": 0,
        "curveFrom": "{0.040000000000001514, 1}",
        "curveMode": 4,
        "curveTo": "{0.055555555555555552, 1}",
        "hasCurveFrom": true,
        "hasCurveTo": false,
        "point": "{0.055555555555555552, 1}"
      },
      {
        "_class": "curvePoint",
        "cornerRadius": 0,
        "curveFrom": "{0.0053703703703696969, 0.97222222222222221}",
        "curveMode": 2,
        "curveTo": "{0.026851851851852696, 0.99444444444444524}",
        "hasCurveFrom": true,
        "hasCurveTo": true,
        "point": "{0.0161111111111133, 0.98333333333333162}"
      },
      {
        "_class": "curvePoint",
        "cornerRadius": 0,
        "curveFrom": "{0, 0.94444444444444442}",
        "curveMode": 4,
        "curveTo": "{0, 0.95925925925925837}",
        "hasCurveFrom": false,
        "hasCurveTo": true,
        "point": "{0, 0.94444444444444442}"
      },
      {
        "_class": "curvePoint",
        "cornerRadius": 0,
        "curveFrom": "{0, 0.040000000000001514}",
        "curveMode": 4,
        "curveTo": "{0, 0.055555555555555552}",
        "hasCurveFrom": true,
        "hasCurveTo": false,
        "point": "{0, 0.055555555555555552}"
      },
      {
        "_class": "curvePoint",
        "cornerRadius": 0,
        "curveFrom": "{0.026851851851852696, 0.0054074074074058577}",
        "curveMode": 2,
        "curveTo": "{0.0053703703703696969, 0.026851851851852696}",
        "hasCurveFrom": true,
        "hasCurveTo": true,
        "point": "{0.0161111111111133, 0.0161111111111133}"
      },
      {
        "_class": "curvePoint",
        "cornerRadius": 0,
        "curveFrom": "{0.055555555555555552, 0}",
        "curveMode": 4,
        "curveTo": "{0.040000000000001514, 0}",
        "hasCurveFrom": false,
        "hasCurveTo": true,
        "point": "{0.055555555555555552, 0}"
      },
      {
        "_class": "curvePoint",
        "cornerRadius": 0,
        "curveFrom": "{0.96000000000000274, 0}",
        "curveMode": 4,
        "curveTo": "{0.94444444444444442, 0}",
        "hasCurveFrom": true,
        "hasCurveTo": false,
        "point": "{0.94444444444444442, 0}"
      },
      {
        "_class": "curvePoint",
        "cornerRadius": 0,
        "curveFrom": "{0.99462962962963031, 0.026851851851852696}",
        "curveMode": 2,
        "curveTo": "{0.97314814814815154, 0.0054074074074058577}",
        "hasCurveFrom": true,
        "hasCurveTo": true,
        "point": "{0.98392592592592709, 0.0161111111111133}"
      },
      {
        "_class": "curvePoint",
        "cornerRadius": 0,
        "curveFrom": "{1, 0.055555555555555552}",
        "curveMode": 4,
        "curveTo": "{1, 0.040000000000001514}",
        "hasCurveFrom": false,
        "hasCurveTo": true,
        "point": "{1, 0.055555555555555552}"
      },
      {
        "_class": "curvePoint",
        "cornerRadius": 0,
        "curveFrom": "{1, 0.95925925925925837}",
        "curveMode": 4,
        "curveTo": "{1, 0.94444444444444442}",
        "hasCurveFrom": true,
        "hasCurveTo": false,
        "point": "{1, 0.94444444444444442}"
      },
      {
        "_class": "curvePoint",
        "cornerRadius": 0,
        "curveFrom": "{0.98392592592592709, 0.98333333333333162}",
        "curveMode": 4,
        "curveTo": "{0.99462962962963031, 0.97222222222222221}",
        "hasCurveFrom": false,
        "hasCurveTo": true,
        "point": "{0.98392592592592709, 0.98333333333333162}"
      }
    ]
  },
  "pointRadiusBehaviour": 0,
  "points": [
    {
      "_class": "curvePoint",
      "cornerRadius": 0,
      "curveFrom": "{0.97314814814815154, 0.99444444444444524}",
      "curveMode": 4,
      "curveTo": "{0.98392592592592709, 0.98333333333333162}",
      "hasCurveFrom": true,
      "hasCurveTo": false,
      "point": "{0.98392592592592709, 0.98333333333333162}"
    },
    {
      "_class": "curvePoint",
      "cornerRadius": 0,
      "curveFrom": "{0.94444444444444442, 1}",
      "curveMode": 4,
      "curveTo": "{0.96000000000000274, 1}",
      "hasCurveFrom": false,
      "hasCurveTo": true,
      "point": "{0.94444444444444442, 1}"
    },
    {
      "_class": "curvePoint",
      "cornerRadius": 0,
      "curveFrom": "{0.040000000000001514, 1}",
      "curveMode": 4,
      "curveTo": "{0.055555555555555552, 1}",
      "hasCurveFrom": true,
      "hasCurveTo": false,
      "point": "{0.055555555555555552, 1}"
    },
    {
      "_class": "curvePoint",
      "cornerRadius": 0,
      "curveFrom": "{0.0053703703703696969, 0.97222222222222221}",
      "curveMode": 2,
      "curveTo": "{0.026851851851852696, 0.99444444444444524}",
      "hasCurveFrom": true,
      "hasCurveTo": true,
      "point": "{0.0161111111111133, 0.98333333333333162}"
    },
    {
      "_class": "curvePoint",
      "cornerRadius": 0,
      "curveFrom": "{0, 0.94444444444444442}",
      "curveMode": 4,
      "curveTo": "{0, 0.95925925925925837}",
      "hasCurveFrom": false,
      "hasCurveTo": true,
      "point": "{0, 0.94444444444444442}"
    },
    {
      "_class": "curvePoint",
      "cornerRadius": 0,
      "curveFrom": "{0, 0.040000000000001514}",
      "curveMode": 4,
      "curveTo": "{0, 0.055555555555555552}",
      "hasCurveFrom": true,
      "hasCurveTo": false,
      "point": "{0, 0.055555555555555552}"
    },
    {
      "_class": "curvePoint",
      "cornerRadius": 0,
      "curveFrom": "{0.026851851851852696, 0.0054074074074058577}",
      "curveMode": 2,
      "curveTo": "{0.0053703703703696969, 0.026851851851852696}",
      "hasCurveFrom": true,
      "hasCurveTo": true,
      "point": "{0.0161111111111133, 0.0161111111111133}"
    },
    {
      "_class": "curvePoint",
      "cornerRadius": 0,
      "curveFrom": "{0.055555555555555552, 0}",
      "curveMode": 4,
      "curveTo": "{0.040000000000001514, 0}",
      "hasCurveFrom": false,
      "hasCurveTo": true,
      "point": "{0.055555555555555552, 0}"
    },
    {
      "_class": "curvePoint",
      "cornerRadius": 0,
      "curveFrom": "{0.96000000000000274, 0}",
      "curveMode": 4,
      "curveTo": "{0.94444444444444442, 0}",
      "hasCurveFrom": true,
      "hasCurveTo": false,
      "point": "{0.94444444444444442, 0}"
    },
    {
      "_class": "curvePoint",
      "cornerRadius": 0,
      "curveFrom": "{0.99462962962963031, 0.026851851851852696}",
      "curveMode": 2,
      "curveTo": "{0.97314814814815154, 0.0054074074074058577}",
      "hasCurveFrom": true,
      "hasCurveTo": true,
      "point": "{0.98392592592592709, 0.0161111111111133}"
    },
    {
      "_class": "curvePoint",
      "cornerRadius": 0,
      "curveFrom": "{1, 0.055555555555555552}",
      "curveMode": 4,
      "curveTo": "{1, 0.040000000000001514}",
      "hasCurveFrom": false,
      "hasCurveTo": true,
      "point": "{1, 0.055555555555555552}"
    },
    {
      "_class": "curvePoint",
      "cornerRadius": 0,
      "curveFrom": "{1, 0.95925925925925837}",
      "curveMode": 4,
      "curveTo": "{1, 0.94444444444444442}",
      "hasCurveFrom": true,
      "hasCurveTo": false,
      "point": "{1, 0.94444444444444442}"
    },
    {
      "_class": "curvePoint",
      "cornerRadius": 0,
      "curveFrom": "{0.98392592592592709, 0.98333333333333162}",
      "curveMode": 4,
      "curveTo": "{0.99462962962963031, 0.97222222222222221}",
      "hasCurveFrom": false,
      "hasCurveTo": true,
      "point": "{0.98392592592592709, 0.98333333333333162}"
    }
  ],
  "resizingConstraint": 63,
  "resizingType": 0,
  "rotation": 0,
  "shouldBreakMaskChain": false
}