{
  "_class": "shapeGroup",
  "clippingMaskMode": 0,
  "do_objectID": "D0AD8C44-3718-4070-98D3-51F64B2B90B2",
  "exportOptions": {
    "_class": "exportOptions",
    "exportFormats": [
    ],
    "includedLayerIds": [
    ],
    "layerOptions": 0,
    "shouldTrim": false
  },
  "frame": {
    "_class": "rect",
    "constrainProportions": false,
    "height": 33,
    "width": 45,
    "x": 0.4740000000001601,
    "y": -0.3790000000000191
  },
  "hasClickThrough": false,
  "hasClippingMask": false,
  "isFlippedHorizontal": false,
  "isFlippedVertical": false,
  "isLocked": false,
  "isVisible": true,
  "layerListExpandedType": 0,
  "layers": [
    {
      "class": "shapePath",
      "id": "47332040-7203-44AC-BEB4-687F3AE1E11C"
    },
    {
      "class": "shapePath",
      "id": "D53819AE-68CE-471D-A944-F331C0946A58"
    }
  ],
  "name": "Fill 115",
  "nameIsFixed": false,
  "originalObjectID": "D0AD8C44-3718-4070-98D3-51F64B2B90B2",
  "resizingConstraint": 63,
  "resizingType": 0,
  "rotation": 0,
  "shouldBreakMaskChain": false,
  "style": {
    "_class": "style",
    "borders": [
      {
        "_class": "border",
        "color": {
          "_class": "color",
          "alpha": 1,
          "blue": 0.592,
          "green": 0.592,
          "red": 0.592
        },
        "fillType": 0,
        "isEnabled": false,
        "position": 0,
        "thickness": 1
      }
    ],
    "do_objectID": "61D6CEDE-82C2-44E7-AEE5-EABC3664577A",
    "endDecorationType": 0,
    "fills": [
      {
        "_class": "fill",
        "color": {
          "_class": "color",
          "alpha": 1,
          "blue": 0.2,
          "green": 0.2,
          "red": 0.2
        },
        "fillType": 0,
        "isEnabled": true,
        "noiseIndex": 0,
        "noiseIntensity": 0,
        "patternFillType": 0,
        "patternTileScale": 1
      }
    ],
    "miterLimit": 10,
    "sharedObjectID": "7CE3F031-47EA-4760-930B-2E7FBF6DF5F3",
    "startDecorationType": 0
  },
  "windingRule": 1
}