{
  "_class": "group",
  "do_objectID": "5DF33868-2F11-4718-BE75-F542AE0B1DBF",
  "exportOptions": {
    "_class": "exportOptions",
    "exportFormats": [
    ],
    "includedLayerIds": [
    ],
    "layerOptions": 0,
    "shouldTrim": false
  },
  "frame": {
    "_class": "rect",
    "constrainProportions": false,
    "height": 200,
    "width": 180,
    "x": 220,
    "y": 1120
  },
  "hasClickThrough": false,
  "isFlippedHorizontal": false,
  "isFlippedVertical": false,
  "isLocked": false,
  "isVisible": true,
  "layerListExpandedType": 0,
  "layers": [
    {
      "class": "shapeGroup",
      "id": "41D85A6F-FEF5-4773-A152-CF47008E406B"
    },
    {
      "class": "shapeGroup",
      "id": "840C10AE-DB59-4A52-B772-768329FC44A0"
    },
    {
      "class": "text",
      "id": "B1782E3F-D475-4CE1-8D2E-B8309A2C45DE"
    },
    {
      "class": "text",
      "id": "724ECB26-7F64-4FBC-A622-6BE326CD42B7"
    },
    {
      "class": "text",
      "id": "874EFD29-D3E7-4190-86BA-11F52C0C823D"
    }
  ],
  "name": "Swatch: #FFCC00",
  "nameIsFixed": false,
  "resizingConstraint": 63,
  "resizingType": 0,
  "rotation": 0,
  "shouldBreakMaskChain": false,
  "style": {
    "_class": "style",
    "endDecorationType": 0,
    "miterLimit": 10,
    "startDecorationType": 0
  }
}