{
  "_class": "shapeGroup",
  "clippingMaskMode": 0,
  "do_objectID": "868D1E78-2E01-481F-98B2-453B7EB8E140",
  "exportOptions": {
    "_class": "exportOptions",
    "exportFormats": [
    ],
    "includedLayerIds": [
    ],
    "layerOptions": 0,
    "shouldTrim": false
  },
  "frame": {
    "_class": "rect",
    "constrainProportions": false,
    "height": 33,
    "width": 33,
    "x": 0.443000000000211,
    "y": -0.3790000000001328
  },
  "hasClickThrough": false,
  "hasClippingMask": false,
  "isFlippedHorizontal": false,
  "isFlippedVertical": false,
  "isLocked": false,
  "isVisible": true,
  "layerListExpandedType": 0,
  "layers": [
    {
      "class": "shapePath",
      "id": "6EF69D23-CABE-4AD0-9644-99E53935A622"
    },
    {
      "class": "shapePath",
      "id": "758DBD60-612F-4968-AB40-984D4E206528"
    },
    {
      "class": "shapePath",
      "id": "1CAEC651-1EAE-404B-B377-79F5E79F0833"
    },
    {
      "class": "shapePath",
      "id": "BA0B52B4-C2B5-464D-A271-ECEAC8C26E63"
    }
  ],
  "name": "Fill 16",
  "nameIsFixed": false,
  "originalObjectID": "868D1E78-2E01-481F-98B2-453B7EB8E140",
  "resizingConstraint": 63,
  "resizingType": 0,
  "rotation": 0,
  "shouldBreakMaskChain": false,
  "style": {
    "_class": "style",
    "borders": [
      {
        "_class": "border",
        "color": {
          "_class": "color",
          "alpha": 1,
          "blue": 0.592,
          "green": 0.592,
          "red": 0.592
        },
        "fillType": 0,
        "isEnabled": false,
        "position": 0,
        "thickness": 1
      }
    ],
    "do_objectID": "F72BDC9A-74A7-4032-AD49-1C2FFE859DBE",
    "endDecorationType": 0,
    "fills": [
      {
        "_class": "fill",
        "color": {
          "_class": "color",
          "alpha": 1,
          "blue": 0.2,
          "green": 0.2,
          "red": 0.2
        },
        "fillType": 0,
        "isEnabled": true,
        "noiseIndex": 0,
        "noiseIntensity": 0,
        "patternFillType": 0,
        "patternTileScale": 1
      }
    ],
    "miterLimit": 10,
    "sharedObjectID": "7CE3F031-47EA-4760-930B-2E7FBF6DF5F3",
    "startDecorationType": 0
  },
  "windingRule": 1
}