{
  "_class": "shapeGroup",
  "clippingMaskMode": 0,
  "do_objectID": "9E3AECB8-EE69-4BE9-B74E-9561BC233D34",
  "exportOptions": {
    "_class": "exportOptions",
    "exportFormats": [
    ],
    "includedLayerIds": [
    ],
    "layerOptions": 0,
    "shouldTrim": false
  },
  "frame": {
    "_class": "rect",
    "constrainProportions": false,
    "height": 32,
    "width": 400,
    "x": 0,
    "y": 0
  },
  "hasClickThrough": false,
  "hasClippingMask": false,
  "isFlippedHorizontal": false,
  "isFlippedVertical": false,
  "isLocked": false,
  "isVisible": true,
  "layerListExpandedType": 0,
  "layers": [
    {
      "class": "rectangle",
      "id": "147F6B40-DA7C-47C0-AB5A-F41EFBD12B7E"
    }
  ],
  "name": "Rectangle 28",
  "nameIsFixed": false,
  "originalObjectID": "9E3AECB8-EE69-4BE9-B74E-9561BC233D34",
  "resizingConstraint": 63,
  "resizingType": 0,
  "rotation": 0,
  "shouldBreakMaskChain": false,
  "style": {
    "_class": "style",
    "borders": [
      {
        "_class": "border",
        "color": {
          "_class": "color",
          "alpha": 1,
          "blue": 0.8,
          "green": 0.8,
          "red": 0.8
        },
        "fillType": 0,
        "isEnabled": true,
        "position": 2,
        "thickness": 1
      }
    ],
    "do_objectID": "24C397FD-DE97-4228-9CC9-6BB1F73737C9",
    "endDecorationType": 0,
    "fills": [
      {
        "_class": "fill",
        "color": {
          "_class": "color",
          "alpha": 1,
          "blue": 1,
          "green": 1,
          "red": 1
        },
        "fillType": 0,
        "isEnabled": true,
        "noiseIndex": 0,
        "noiseIntensity": 0,
        "patternFillType": 0,
        "patternTileScale": 1
      }
    ],
    "miterLimit": 10,
    "shadows": [
      {
        "_class": "shadow",
        "blurRadius": 1,
        "color": {
          "_class": "color",
          "alpha": 0.08,
          "blue": 0,
          "green": 0,
          "red": 0
        },
        "contextSettings": {
          "_class": "graphicsContextSettings",
          "blendMode": 0,
          "opacity": 1
        },
        "isEnabled": true,
        "offsetX": 0,
        "offsetY": 0,
        "spread": 0
      }
    ],
    "sharedObjectID": "4AAAC95E-D5C4-49FB-9357-369ECD8EF25F",
    "startDecorationType": 0
  },
  "windingRule": 1
}