{
  "_class": "shapeGroup",
  "clippingMaskMode": 0,
  "do_objectID": "5A9F7BC4-E793-41BB-9F4B-B5A7FB30BD3F",
  "exportOptions": {
    "_class": "exportOptions",
    "exportFormats": [
    ],
    "includedLayerIds": [
    ],
    "layerOptions": 0,
    "shouldTrim": false
  },
  "frame": {
    "_class": "rect",
    "constrainProportions": false,
    "height": 18,
    "width": 26,
    "x": 213,
    "y": 11
  },
  "hasClickThrough": false,
  "hasClippingMask": false,
  "isFlippedHorizontal": false,
  "isFlippedVertical": false,
  "isLocked": false,
  "isVisible": true,
  "layerListExpandedType": 0,
  "layers": [
    {
      "class": "rectangle",
      "id": "54EAFCD4-7B6C-4070-B93A-6D93392765ED"
    }
  ],
  "name": "Rectangle 280",
  "nameIsFixed": false,
  "originalObjectID": "5A9F7BC4-E793-41BB-9F4B-B5A7FB30BD3F",
  "resizingConstraint": 63,
  "resizingType": 0,
  "rotation": 0,
  "shouldBreakMaskChain": false,
  "style": {
    "_class": "style",
    "do_objectID": "F125D5E1-3422-4FD3-BD1F-8DB69010F557",
    "endDecorationType": 0,
    "fills": [
      {
        "_class": "fill",
        "color": {
          "_class": "color",
          "alpha": 1,
          "blue": 1,
          "green": 1,
          "red": 1
        },
        "fillType": 0,
        "isEnabled": true,
        "noiseIndex": 0,
        "noiseIntensity": 0,
        "patternFillType": 0,
        "patternTileScale": 1
      }
    ],
    "miterLimit": 10,
    "sharedObjectID": "605054BB-4145-40F0-9E1F-A464EE76A2CE",
    "startDecorationType": 0
  },
  "windingRule": 1
}