{
  "_class": "shapeGroup",
  "clippingMaskMode": 0,
  "do_objectID": "E11F2458-96B1-4CD2-B4C3-96886F13A2F5",
  "exportOptions": {
    "_class": "exportOptions",
    "exportFormats": [
    ],
    "includedLayerIds": [
    ],
    "layerOptions": 0,
    "shouldTrim": false
  },
  "frame": {
    "_class": "rect",
    "constrainProportions": false,
    "height": 35.81999999999994,
    "width": 35.82000000000005,
    "x": -0.4669999999996435,
    "y": -0.2889999999999873
  },
  "hasClickThrough": false,
  "hasClippingMask": false,
  "isFlippedHorizontal": false,
  "isFlippedVertical": false,
  "isLocked": false,
  "isVisible": true,
  "layerListExpandedType": 0,
  "layers": [
    {
      "class": "shapePath",
      "id": "9ACF90B5-F2AC-4876-8827-0D44D268B806"
    },
    {
      "class": "shapePath",
      "id": "FBD640B3-9FA7-45D1-B0E6-62CBA50415FD"
    },
    {
      "class": "shapePath",
      "id": "23CF565C-763F-4CC6-AD50-16BD49275F6F"
    }
  ],
  "name": "Fill 87",
  "nameIsFixed": false,
  "originalObjectID": "E11F2458-96B1-4CD2-B4C3-96886F13A2F5",
  "resizingConstraint": 63,
  "resizingType": 0,
  "rotation": 0,
  "shouldBreakMaskChain": false,
  "style": {
    "_class": "style",
    "borders": [
      {
        "_class": "border",
        "color": {
          "_class": "color",
          "alpha": 1,
          "blue": 0.592,
          "green": 0.592,
          "red": 0.592
        },
        "fillType": 0,
        "isEnabled": false,
        "position": 0,
        "thickness": 1
      }
    ],
    "do_objectID": "2586AAEB-AFD8-45B2-8EA6-682AFAC1D4AE",
    "endDecorationType": 0,
    "fills": [
      {
        "_class": "fill",
        "color": {
          "_class": "color",
          "alpha": 1,
          "blue": 0.2,
          "green": 0.2,
          "red": 0.2
        },
        "fillType": 0,
        "isEnabled": true,
        "noiseIndex": 0,
        "noiseIntensity": 0,
        "patternFillType": 0,
        "patternTileScale": 1
      }
    ],
    "miterLimit": 10,
    "sharedObjectID": "7CE3F031-47EA-4760-930B-2E7FBF6DF5F3",
    "startDecorationType": 0
  },
  "windingRule": 1
}